<annotation>
  <folder>img</folder>
  <filename>mut_ndah.jpg</filename>
  <path>C:/Python/PyCharm/Test/image_processing/img/mut_ndah.jpg</path>
  <source>
    <database>Unknown</database>
  </source>
  <size>
    <width>1477</width>
    <height>1108</height>
    <depth>3</depth>
  </size>
  <segmented>0</segmented>
  <object>
    <name>face</name>
    <pose>Unspecified</pose>
    <truncated>0</truncated>
    <difficult>0</difficult>
    <bndbox>
      <xmin>1064</xmin>
      <ymin>322</ymin>
      <xmax>1260</xmax>
      <ymax>518</ymax>
    </bndbox>
  </object>
  <object>
    <name>face</name>
    <pose>Unspecified</pose>
    <truncated>0</truncated>
    <difficult>0</difficult>
    <bndbox>
      <xmin>624</xmin>
      <ymin>365</ymin>
      <xmax>983</xmax>
      <ymax>724</ymax>
    </bndbox>
  </object>
</annotation>
